noaa_sdk/__init__.py
noaa_sdk/accept.py
noaa_sdk/ncdc.py
noaa_sdk/noaa.py
noaa_sdk/util.py
noaa_sdk-0.1.21.dist-info/LICENSE
noaa_sdk-0.1.21.dist-info/METADATA
noaa_sdk-0.1.21.dist-info/WHEEL
noaa_sdk-0.1.21.dist-info/top_level.txt
noaa_sdk-0.1.21.dist-info/RECORD
