Metadata-Version: 1.1
Name: noaa-sdk
Version: 0.1.21
Summary: NOAA API (V3) Python 3 SDK.
Home-page: https://github.com/paulokuong/noaa
Author: Paulo Kuong
Author-email: paulo.kuong@gmail.com
License: MIT
Keywords: NOAA noaa weather public v3 api sdk osm postalcode country postcode
Platform: UNKNOWN
Classifier: Development Status :: 3 - Alpha
Classifier: License :: OSI Approved :: MIT License
Classifier: Programming Language :: Python :: 3.4
